slh/cli.py
slh/config.py
slh/download_manager.py
slh/factory.py
slh/template_engine.py
slh/utils.py
slh/validation.py
silhouette_cli-1.0.3.dist-info/LICENSE
silhouette_cli-1.0.3.dist-info/METADATA
silhouette_cli-1.0.3.dist-info/WHEEL
silhouette_cli-1.0.3.dist-info/entry_points.txt
silhouette_cli-1.0.3.dist-info/top_level.txt
silhouette_cli-1.0.3.dist-info/RECORD
